subtitlekit/__init__.py
subtitlekit/_version.py
subtitlekit/updater.py
subtitlekit/cli/__init__.py
subtitlekit/cli/main.py
subtitlekit/core/__init__.py
subtitlekit/core/cleaner.py
subtitlekit/core/encoding.py
subtitlekit/core/preprocessor.py
subtitlekit/tools/__init__.py
subtitlekit/tools/apply_annotations.py
subtitlekit/tools/corrections.py
subtitlekit/tools/enhanced_matcher.py
subtitlekit/tools/matcher.py
subtitlekit/tools/overlaps.py
subtitlekit/tools/reading_speed.py
subtitlekit/ui/__init__.py
subtitlekit/ui/colab.py
subtitlekit/ui/colab.py.bak
subtitlekit/ui/desktop.py
subtitlekit/ui/locales/el.json
subtitlekit/ui/locales/en.json
subtitlekit-0.1.7.dist-info/licenses/LICENSE
subtitlekit-0.1.7.dist-info/METADATA
subtitlekit-0.1.7.dist-info/WHEEL
subtitlekit-0.1.7.dist-info/entry_points.txt
subtitlekit-0.1.7.dist-info/top_level.txt
subtitlekit-0.1.7.dist-info/RECORD
