Metadata-Version: 2.4
Name: subtitlekit
Version: 0.1.7
Summary: Subtitle processing toolkit: merge, sync, fix overlaps, and apply corrections
Author-email: angelospk <haroldpoigr@gmail.com>
License: MIT
Project-URL: Homepage, https://github.com/angelospk/subtitlekit
Project-URL: Repository, https://github.com/angelospk/subtitlekit
Project-URL: Issues, https://github.com/angelospk/subtitlekit/issues
Keywords: subtitles,srt,synchronization,translation,processing
Classifier: Development Status :: 4 - Beta
Classifier: Intended Audience :: Developers
Classifier: License :: OSI Approved :: MIT License
Classifier: Programming Language :: Python :: 3
Classifier: Programming Language :: Python :: 3.8
Classifier: Programming Language :: Python :: 3.9
Classifier: Programming Language :: Python :: 3.10
Classifier: Programming Language :: Python :: 3.11
Classifier: Programming Language :: Python :: 3.12
Classifier: Topic :: Multimedia :: Video
Classifier: Topic :: Text Processing
Requires-Python: >=3.8
License-File: LICENSE
Requires-Dist: pysrt>=1.1.2
Requires-Dist: chardet>=5.0.0
Requires-Dist: ffsubsync>=0.4.0
Requires-Dist: requests>=2.28.0
Requires-Dist: packaging>=21.0
Provides-Extra: dev
Requires-Dist: pytest>=7.0.0; extra == "dev"
Requires-Dist: pytest-cov>=4.0.0; extra == "dev"
Provides-Extra: ui
Requires-Dist: ipywidgets>=8.0.0; extra == "ui"
Dynamic: license-file
